pyocto/__init__.py
pyocto/_core.cp39-win_amd64.pyd
pyocto/associator.py
pyocto-0.1.9.dist-info/METADATA
pyocto-0.1.9.dist-info/WHEEL
pyocto-0.1.9.dist-info/licenses/LICENSE
pyocto-0.1.9.dist-info/RECORD
