Metadata-Version: 2.2
Name: pyocto
Version: 0.1.9
Summary: A high-throughput seismic phase associator
Author-Email: My Name <me@email.com>
Classifier: Development Status :: 4 - Beta
Classifier: License :: OSI Approved :: MIT License
Classifier: Programming Language :: Python :: 3 :: Only
Classifier: Programming Language :: Python :: 3.9
Classifier: Programming Language :: Python :: 3.10
Classifier: Programming Language :: Python :: 3.11
Requires-Python: >=3.9
Requires-Dist: numpy>=1.21.6
Requires-Dist: pandas>=1.1
Requires-Dist: numpy<2
Requires-Dist: pyproj
Provides-Extra: test
Requires-Dist: pytest>=7.4.2; extra == "test"
Requires-Dist: pyrocko>=2023.06.29; extra == "test"
Requires-Dist: pyarrow>=12.0.1; extra == "test"
